fundanalyz/__init__.py
fundanalyz/index_dump.py
fundquant/__init__.py
fundquant/dao/__init__.py
fundquant/dao/jsl_data.py
fundquant/data_get/__init__.py
fundquant/data_get/jsl_data.py
fundquant/data_get/lixinren_data.py
fundquant/data_get/lxr_merge_jsl.py
fundquant/data_get/xq_data.py
fundquant/domain/__init__.py
fundquant/domain/etf_track.py
fundquant/domain/index_track.py
fundquant/domain/send_email.py
fundquant/main_interface/__init__.py
fundquant/main_interface/jobs.py
fundquant/main_interface/monitor.py
fundquant/model/__init__.py
fundquant/model/data/__init__.py
fundquant/model/data/data_dump.py
fundquant/model/preprocess/__init__.py
fundquant/model/preprocess/feature_gen.py
fundquant/model/preprocess/preprocess.py
fundquant/model/train/__init__.py
fundquant/model/train/model_train.py
fundquant/service/__init__.py
fundquant/service/etf_value_statistic.py
fundquant/service/strategy.py
fundquant/util/__init__.py
fundquant/util/date_util.py
fundquant/util/index_update.py
fundquant/util/tushare_data.py
fundquant-4.5.dist-info/LICENSE
fundquant-4.5.dist-info/METADATA
fundquant-4.5.dist-info/WHEEL
fundquant-4.5.dist-info/top_level.txt
fundquant-4.5.dist-info/RECORD
