Metadata-Version: 2.1
Name: fundquant
Version: 4.5
Summary: 指数基金量化
Home-page: UNKNOWN
Author: Murphy xiaoxi
Author-email: murphyxiaoxi@outlook.com
License: UNKNOWN
Platform: UNKNOWN
Classifier: Programming Language :: Python :: 3
Classifier: License :: OSI Approved :: MIT License
Classifier: Operating System :: OS Independent
Requires-Python: >=3.6
